xtlib/__init__.py
xtlib/attach.py
xtlib/box_helper.py
xtlib/box_information.py
xtlib/box_secrets.py
xtlib/cache_client.py
xtlib/cache_server.py
xtlib/capture.py
xtlib/client.py
xtlib/cmd_core.py
xtlib/console.py
xtlib/constants.py
xtlib/controller.py
xtlib/errors.py
xtlib/file_utils.py
xtlib/impl_base.py
xtlib/impl_compute.py
xtlib/impl_help.py
xtlib/impl_shared.py
xtlib/impl_storage.py
xtlib/impl_storage_api.py
xtlib/impl_utilities.py
xtlib/job_helper.py
xtlib/metric_set.py
xtlib/mirror.py
xtlib/mirror_worker.py
xtlib/pc_utils.py
xtlib/plot_builder.py
xtlib/process_utils.py
xtlib/qfe.py
xtlib/repair_runs.py
xtlib/report_builder.py
xtlib/run.py
xtlib/run_helper.py
xtlib/run_info.py
xtlib/runner.py
xtlib/scriptor.py
xtlib/tensorboard_reader.py
xtlib/utils.py
xtlib/xt_client.py
xtlib/xt_cmds.py
xtlib/xt_dict.py
xtlib/xt_run.py
xtlib/xt_server.py
xtlib/xt_vault.py
xtlib/backends/__init__.py
xtlib/backends/aml_shim.py
xtlib/backends/backend_aml.py
xtlib/backends/backend_base.py
xtlib/backends/backend_batch.py
xtlib/backends/backend_interface.py
xtlib/backends/backend_pool.py
xtlib/demo_files/commands_advanced.py
xtlib/demo_files/commands_basic.py
xtlib/demo_files/xt_config.yaml
xtlib/demo_files/xt_demo.py
xtlib/demo_files/code/empty.py
xtlib/demo_files/code/miniMnist.py
xtlib/demo_files/code/miniSweeps.yaml
xtlib/demo_files/code/multi_commands.txt
xtlib/help_topics/internals/config_schema.rst
xtlib/help_topics/internals/quick_front_end.rst
xtlib/help_topics/internals/remote_control.rst
xtlib/help_topics/internals/xt_build.rst
xtlib/help_topics/internals/xt_dev.rst
xtlib/help_topics/internals/xt_release.rst
xtlib/help_topics/topics/cmd_options.rst
xtlib/help_topics/topics/compute_node_reqs.rst
xtlib/help_topics/topics/creating_xt_services.rst
xtlib/help_topics/topics/defining_your_config_file.rst
xtlib/help_topics/topics/extend_commands.rst
xtlib/help_topics/topics/extend_compute.rst
xtlib/help_topics/topics/extend_hp_search.rst
xtlib-1.0.0.dist-info/LICENSE.txt
xtlib-1.0.0.dist-info/METADATA
xtlib-1.0.0.dist-info/NOTICE.md
xtlib-1.0.0.dist-info/WHEEL
xtlib-1.0.0.dist-info/entry_points.txt
xtlib-1.0.0.dist-info/top_level.txt
xtlib-1.0.0.dist-info/RECORD
