Metadata-Version: 2.1
Name: xtlib
Version: 1.0.0
Summary: A set of tools for organizing and scaling ML experiments
Home-page: https://github.com/rfernand2
Author: Roland Fernandez
Author-email: rfernand@microsoft.com
License: UNKNOWN
Platform: UNKNOWN
Classifier: Programming Language :: Python :: 3
Classifier: License :: OSI Approved :: MIT License
Classifier: Operating System :: OS Independent
Requires-Dist: azureml-sdk (==1.0.69)
Requires-Dist: azure-storage-blob (==2.1.0)
Requires-Dist: azure-identity (==1.2.0)
Requires-Dist: azure-keyvault (==4.0.0)
Requires-Dist: azure-batch (==8.0.0)
Requires-Dist: azureml-widgets (==1.0.69.1)
Requires-Dist: numpy
Requires-Dist: arrow (==0.14.0)
Requires-Dist: rpyc (==4.1.2)
Requires-Dist: future
Requires-Dist: watchdog (==0.9.0)
Requires-Dist: hyperopt
Requires-Dist: pymongo
Requires-Dist: tqdm
Requires-Dist: tensorboard (==2.1.0)
Requires-Dist: psutil
Requires-Dist: ptvsd
Requires-Dist: matplotlib
Requires-Dist: seaborn
Requires-Dist: pandas
Requires-Dist: PyYAML (>=5.1.0)
Requires-Dist: python-interface
Requires-Dist: paramiko
Requires-Dist: grpcio (>=1.24.3)
Requires-Dist: ruamel.yaml (==0.15.89)
Requires-Dist: scikit-learn
Requires-Dist: pyasn1 (>=0.4.6)
Provides-Extra: dev
Requires-Dist: sphinx ; extra == 'dev'
Requires-Dist: sphinx-rtd-theme ; extra == 'dev'
